{"objects":[{"anchor":{"x":0,"y":0},"children":[{"position":{"x":375,"y":630.61},"children":[],"type":"ButtonObject","properties":{"width":195,"height":59,"padding":"20","backgroundName":"_default_button","backgroundColorNormal":"#8E93BF","onMouseUp":"fn this.goTo('TestScreen')"},"txt":"Click","style":{"fill":"#ffffff"}},{"position":{"x":363.02,"y":229.75},"type":"ImageObject","constraintX":"app.width/2","imageName":"dragon"}],"type":"Layer","name":"Default Layer","factor":1,"isActive":true,"isInputContent":true}],"screenPosition":{"x":141.13,"y":19.67},"fileName":"main_screen.json","previewScreenName":"mainScreen","layoutType":"screen"}